setup.py
scripts/wnyc_dns
wnyc_dns/__init__.py
wnyc_dns/common.py
wnyc_dns/rackspace.py
wnyc_dns/route53.py
wnyc_dns.egg-info/PKG-INFO
wnyc_dns.egg-info/SOURCES.txt
wnyc_dns.egg-info/dependency_links.txt
wnyc_dns.egg-info/requires.txt
wnyc_dns.egg-info/top_level.txt
wnyc_dns.egg-info/zip-safe