Metadata-Version: 1.0
Name: wnyc-dns
Version: 0.0.0
Summary: Tools to help you leave rackspace
Home-page: UNKNOWN
Author: Adam DePrince
Author-email: adeprince@nypublicradio.org
License: GPLv3
Platform: UNKNOWN
